Droxic.py
Droxic-0.2.dist-info/METADATA
Droxic-0.2.dist-info/WHEEL
Droxic-0.2.dist-info/top_level.txt
Droxic-0.2.dist-info/RECORD
